MANIFEST.in
setup.py
/home/scopatz/polyphemus/scripts/polyphemus
polyphemus/__init__.py
polyphemus/apache2.py
polyphemus/base.py
polyphemus/batlab.py
polyphemus/batlabbase.py
polyphemus/batlabrun.py
polyphemus/batlabstat.py
polyphemus/dashboard.py
polyphemus/event.py
polyphemus/github.py
polyphemus/githubbase.py
polyphemus/githubhook.py
polyphemus/githubstat.py
polyphemus/main.py
polyphemus/plugins.py
polyphemus/utils.py
polyphemus/version.py
polyphemus.egg-info/PKG-INFO
polyphemus.egg-info/SOURCES.txt
polyphemus.egg-info/dependency_links.txt
polyphemus.egg-info/not-zip-safe
polyphemus.egg-info/requires.txt
polyphemus.egg-info/top_level.txt
polyphemus/templates/github_dashboard.html
scripts/polyphemus