Metadata-Version: 1.1
Name: polyphemus
Version: 0.1
Summary: A BaTLaB itegration service for repo hosting sites like GitHub.
Home-page: http://polyphemus.org/
Author: Anthony Scopatz
Author-email: scopatz@gmail.com
License: UNKNOWN
Download-URL: https://github.com/polyphemus-ci/polyphemus/zipball/0.1
Platform: UNKNOWN
Classifier: License :: OSI Approved :: BSD License
Classifier: Intended Audience :: Developers
Classifier: Programming Language :: Python :: 2
Classifier: Programming Language :: Python :: 3
Classifier: Topic :: Utilities
Classifier: Topic :: Software Development :: Build Tools
Classifier: Topic :: Software Development :: Quality Assurance
Classifier: Topic :: Software Development :: Testing
